{"@context":"https://linked.art/ns/v1/linked-art.json","id":"https://www.moma.org/data/activity/1140","type":"Activity","classified_as":[{"id":"http://vocab.getty.edu/aat/300054766","type":"Type","_label":"Exhibiting"}],"identified_by":[{"type":"Name","classified_as":[{"id":"http://vocab.getty.edu/aat/300404670","type":"Type","_label":"Primary Name"}],"content":"Landscape"}],"carried_out_by":[{"id":"https://www.moma.org/data/group/inst3","type":"Group"},{"id":"https://www.moma.org/data/person/26888","type":"Person"}],"subject_of":[{"type":"LinguisticObject"}],"influenced_by":[{"id":"https://www.moma.org/data/person/3721","type":"Person"},{"id":"https://www.moma.org/data/person/2890","type":"Person"},{"id":"https://www.moma.org/data/person/5310","type":"Person"},{"id":"https://www.moma.org/data/person/4887","type":"Person"},{"id":"https://www.moma.org/data/person/4513","type":"Person"},{"id":"https://www.moma.org/data/person/5283","type":"Person"},{"id":"https://www.moma.org/data/person/4020","type":"Person"},{"id":"https://www.moma.org/data/person/4241","type":"Person"},{"id":"https://www.moma.org/data/person/5416","type":"Person"},{"id":"https://www.moma.org/data/person/3942","type":"Person"},{"id":"https://www.moma.org/data/person/3950","type":"Person"},{"id":"https://www.moma.org/data/person/5385","type":"Person"},{"id":"https://www.moma.org/data/person/6309","type":"Person"},{"id":"https://www.moma.org/data/person/7155","type":"Person"},{"id":"https://www.moma.org/data/person/6023","type":"Person"},{"id":"https://www.moma.org/data/person/18848","type":"Person"},{"id":"https://www.moma.org/data/person/32728","type":"Person"},{"id":"https://www.moma.org/data/person/32721","type":"Person"},{"id":"https://www.moma.org/data/person/32717","type":"Person"},{"id":"https://www.moma.org/data/person/32718","type":"Person"},{"id":"https://www.moma.org/data/person/32719","type":"Person"},{"id":"https://www.moma.org/data/person/30692","type":"Person"},{"id":"https://www.moma.org/data/person/32726","type":"Person"},{"id":"https://www.moma.org/data/person/32245","type":"Person"},{"id":"https://www.moma.org/data/person/32722","type":"Person"},{"id":"https://www.moma.org/data/person/32723","type":"Person"},{"id":"https://www.moma.org/data/person/32724","type":"Person"},{"id":"https://www.moma.org/data/person/32725","type":"Person"},{"id":"https://www.moma.org/data/person/32729","type":"Person"},{"id":"https://www.moma.org/data/person/32727","type":"Person"},{"id":"https://www.moma.org/data/person/32720","type":"Person"},{"id":"https://www.moma.org/data/person/1462","type":"Person"},{"id":"https://www.moma.org/data/person/1907","type":"Person"},{"id":"https://www.moma.org/data/person/2569","type":"Person"},{"id":"https://www.moma.org/data/person/2754","type":"Person"},{"id":"https://www.moma.org/data/person/695","type":"Person"},{"id":"https://www.moma.org/data/person/1532","type":"Person"},{"id":"https://www.moma.org/data/person/1086","type":"Person"},{"id":"https://www.moma.org/data/person/1068","type":"Person"},{"id":"https://www.moma.org/data/person/378","type":"Person"},{"id":"https://www.moma.org/data/person/34615","type":"Person"},{"id":"https://www.moma.org/data/person/61428","type":"Person"},{"id":"https://www.moma.org/data/person/73626","type":"Person"}]}