{"@context":"https://linked.art/ns/v1/linked-art.json","id":"https://www.moma.org/data/activity/1666","type":"Activity","classified_as":[{"id":"http://vocab.getty.edu/aat/300054766","type":"Type","_label":"Exhibiting"}],"identified_by":[{"type":"Name","classified_as":[{"id":"http://vocab.getty.edu/aat/300404670","type":"Type","_label":"Primary Name"}],"content":"BERLINART 1961–1987"}],"carried_out_by":[{"id":"https://www.moma.org/data/group/inst3","type":"Group"},{"id":"https://www.moma.org/data/group/35708","type":"Group"}],"subject_of":[{"type":"LinguisticObject"}],"influenced_by":[{"id":"https://www.moma.org/data/person/3488","type":"Person"},{"id":"https://www.moma.org/data/person/2983","type":"Person"},{"id":"https://www.moma.org/data/person/4706","type":"Person"},{"id":"https://www.moma.org/data/person/2872","type":"Person"},{"id":"https://www.moma.org/data/person/2960","type":"Person"},{"id":"https://www.moma.org/data/person/3942","type":"Person"},{"id":"https://www.moma.org/data/person/4839","type":"Person"},{"id":"https://www.moma.org/data/person/4597","type":"Person"},{"id":"https://www.moma.org/data/person/4602","type":"Person"},{"id":"https://www.moma.org/data/person/3733","type":"Person"},{"id":"https://www.moma.org/data/person/5352","type":"Person"},{"id":"https://www.moma.org/data/person/18760","type":"Person"},{"id":"https://www.moma.org/data/person/22337","type":"Person"},{"id":"https://www.moma.org/data/person/18759","type":"Person"},{"id":"https://www.moma.org/data/person/22908","type":"Person"},{"id":"https://www.moma.org/data/person/18202","type":"Person"},{"id":"https://www.moma.org/data/person/17393","type":"Person"},{"id":"https://www.moma.org/data/person/13010","type":"Person"},{"id":"https://www.moma.org/data/person/5844","type":"Person"},{"id":"https://www.moma.org/data/person/5848","type":"Person"},{"id":"https://www.moma.org/data/person/13011","type":"Person"},{"id":"https://www.moma.org/data/group/10678","type":"Group"},{"id":"https://www.moma.org/data/person/6088","type":"Person"},{"id":"https://www.moma.org/data/person/5914","type":"Person"},{"id":"https://www.moma.org/data/person/6343","type":"Person"},{"id":"https://www.moma.org/data/person/5452","type":"Person"},{"id":"https://www.moma.org/data/group/18217","type":"Group"},{"id":"https://www.moma.org/data/person/7129","type":"Person"},{"id":"https://www.moma.org/data/person/6334","type":"Person"},{"id":"https://www.moma.org/data/person/57128","type":"Person"},{"id":"https://www.moma.org/data/person/32941","type":"Person"},{"id":"https://www.moma.org/data/person/33214","type":"Person"},{"id":"https://www.moma.org/data/person/33222","type":"Person"},{"id":"https://www.moma.org/data/person/33212","type":"Person"},{"id":"https://www.moma.org/data/person/33213","type":"Person"},{"id":"https://www.moma.org/data/person/33216","type":"Person"},{"id":"https://www.moma.org/data/person/32934","type":"Person"},{"id":"https://www.moma.org/data/person/33218","type":"Person"},{"id":"https://www.moma.org/data/person/33223","type":"Person"},{"id":"https://www.moma.org/data/person/33219","type":"Person"},{"id":"https://www.moma.org/data/person/33215","type":"Person"},{"id":"https://www.moma.org/data/person/32923","type":"Person"},{"id":"https://www.moma.org/data/person/33220","type":"Person"},{"id":"https://www.moma.org/data/person/32936","type":"Person"},{"id":"https://www.moma.org/data/person/33217","type":"Person"},{"id":"https://www.moma.org/data/person/1614","type":"Person"},{"id":"https://www.moma.org/data/person/724","type":"Person"},{"id":"https://www.moma.org/data/person/2382","type":"Person"},{"id":"https://www.moma.org/data/person/2569","type":"Person"},{"id":"https://www.moma.org/data/person/2568","type":"Person"},{"id":"https://www.moma.org/data/person/800","type":"Person"},{"id":"https://www.moma.org/data/person/345","type":"Person"},{"id":"https://www.moma.org/data/person/1792","type":"Person"},{"id":"https://www.moma.org/data/person/728","type":"Person"},{"id":"https://www.moma.org/data/person/652","type":"Person"},{"id":"https://www.moma.org/data/person/515","type":"Person"},{"id":"https://www.moma.org/data/person/205","type":"Person"},{"id":"https://www.moma.org/data/person/1881","type":"Person"},{"id":"https://www.moma.org/data/person/1787","type":"Person"},{"id":"https://www.moma.org/data/person/1068","type":"Person"}]}