{"@context":"https://linked.art/ns/v1/linked-art.json","id":"https://www.moma.org/data/activity/17062","type":"Activity","classified_as":[{"id":"http://vocab.getty.edu/aat/300054766","type":"Type","_label":"Exhibiting"}],"identified_by":[{"type":"Name","classified_as":[{"id":"http://vocab.getty.edu/aat/300404670","type":"Type","_label":"Primary Name"}],"content":"Unmonumental: The Object in the 21st Century"}],"carried_out_by":[{"id":"https://www.moma.org/data/group/inst13","type":"Group"},{"id":"https://www.moma.org/data/person/66468","type":"Person"},{"id":"https://www.moma.org/data/person/65868","type":"Person"},{"id":"https://www.moma.org/data/person/27013","type":"Person"}],"subject_of":[{"type":"LinguisticObject"}],"influenced_by":[{"id":"https://www.moma.org/data/person/17617","type":"Person"},{"id":"https://www.moma.org/data/person/19785","type":"Person"},{"id":"https://www.moma.org/data/person/18882","type":"Person"},{"id":"https://www.moma.org/data/person/18292","type":"Person"},{"id":"https://www.moma.org/data/person/17832","type":"Person"},{"id":"https://www.moma.org/data/person/17819","type":"Person"},{"id":"https://www.moma.org/data/person/17668","type":"Person"},{"id":"https://www.moma.org/data/person/21715","type":"Person"},{"id":"https://www.moma.org/data/person/14618","type":"Person"},{"id":"https://www.moma.org/data/person/14483","type":"Person"},{"id":"https://www.moma.org/data/person/8046","type":"Person"},{"id":"https://www.moma.org/data/person/7475","type":"Person"},{"id":"https://www.moma.org/data/person/7431","type":"Person"},{"id":"https://www.moma.org/data/person/17740","type":"Person"},{"id":"https://www.moma.org/data/person/61269","type":"Person"},{"id":"https://www.moma.org/data/person/66194","type":"Person"},{"id":"https://www.moma.org/data/person/65746","type":"Person"},{"id":"https://www.moma.org/data/person/65508","type":"Person"},{"id":"https://www.moma.org/data/person/19795","type":"Person"},{"id":"https://www.moma.org/data/person/63803","type":"Person"},{"id":"https://www.moma.org/data/person/20543","type":"Person"},{"id":"https://www.moma.org/data/person/60078","type":"Person"},{"id":"https://www.moma.org/data/person/58943","type":"Person"},{"id":"https://www.moma.org/data/person/35101","type":"Person"},{"id":"https://www.moma.org/data/person/25577","type":"Person"},{"id":"https://www.moma.org/data/person/25525","type":"Person"},{"id":"https://www.moma.org/data/person/24671","type":"Person"},{"id":"https://www.moma.org/data/person/17679","type":"Person"},{"id":"https://www.moma.org/data/person/64213","type":"Person"},{"id":"https://www.moma.org/data/person/17765","type":"Person"}]}