{"@context":"https://linked.art/ns/v1/linked-art.json","id":"https://www.moma.org/data/activity/1945","type":"Activity","classified_as":[{"id":"http://vocab.getty.edu/aat/300054766","type":"Type","_label":"Exhibiting"}],"identified_by":[{"type":"Name","classified_as":[{"id":"http://vocab.getty.edu/aat/300404670","type":"Type","_label":"Primary Name"}],"content":"Sense and Sensibility: Women Artists and Minimalism in the 90s"}],"carried_out_by":[{"id":"https://www.moma.org/data/group/inst3","type":"Group"},{"id":"https://www.moma.org/data/person/27191","type":"Person"}],"subject_of":[{"type":"LinguisticObject"}],"influenced_by":[{"id":"https://www.moma.org/data/person/7912","type":"Person"},{"id":"https://www.moma.org/data/person/6340","type":"Person"},{"id":"https://www.moma.org/data/person/6603","type":"Person"},{"id":"https://www.moma.org/data/person/26993","type":"Person"},{"id":"https://www.moma.org/data/person/7156","type":"Person"},{"id":"https://www.moma.org/data/person/35891","type":"Person"},{"id":"https://www.moma.org/data/person/35892","type":"Person"}]}