{"@context":"https://linked.art/ns/v1/linked-art.json","id":"https://www.moma.org/data/activity/1972","type":"Activity","classified_as":[{"id":"http://vocab.getty.edu/aat/300054766","type":"Type","_label":"Exhibiting"}],"identified_by":[{"type":"Name","classified_as":[{"id":"http://vocab.getty.edu/aat/300404670","type":"Type","_label":"Primary Name"}],"content":"Recent Acquisitions: Photography"}],"carried_out_by":[{"id":"https://www.moma.org/data/group/inst3","type":"Group"}],"subject_of":[{"type":"LinguisticObject"}],"influenced_by":[{"id":"https://www.moma.org/data/person/5183","type":"Person"},{"id":"https://www.moma.org/data/person/4527","type":"Person"},{"id":"https://www.moma.org/data/person/4370","type":"Person"},{"id":"https://www.moma.org/data/person/5284","type":"Person"},{"id":"https://www.moma.org/data/person/4164","type":"Person"},{"id":"https://www.moma.org/data/person/3718","type":"Person"},{"id":"https://www.moma.org/data/person/4780","type":"Person"},{"id":"https://www.moma.org/data/person/3657","type":"Person"},{"id":"https://www.moma.org/data/person/4086","type":"Person"},{"id":"https://www.moma.org/data/person/2944","type":"Person"},{"id":"https://www.moma.org/data/person/7682","type":"Person"},{"id":"https://www.moma.org/data/person/7335","type":"Person"},{"id":"https://www.moma.org/data/person/7687","type":"Person"},{"id":"https://www.moma.org/data/person/7337","type":"Person"},{"id":"https://www.moma.org/data/person/7681","type":"Person"},{"id":"https://www.moma.org/data/person/6005","type":"Person"},{"id":"https://www.moma.org/data/group/7671","type":"Group"},{"id":"https://www.moma.org/data/person/7293","type":"Person"},{"id":"https://www.moma.org/data/person/6589","type":"Person"},{"id":"https://www.moma.org/data/person/7688","type":"Person"},{"id":"https://www.moma.org/data/person/6682","type":"Person"},{"id":"https://www.moma.org/data/person/6110","type":"Person"},{"id":"https://www.moma.org/data/person/7535","type":"Person"},{"id":"https://www.moma.org/data/person/7326","type":"Person"},{"id":"https://www.moma.org/data/person/7291","type":"Person"},{"id":"https://www.moma.org/data/person/7666","type":"Person"},{"id":"https://www.moma.org/data/person/7319","type":"Person"},{"id":"https://www.moma.org/data/person/7316","type":"Person"},{"id":"https://www.moma.org/data/person/6839","type":"Person"},{"id":"https://www.moma.org/data/person/8029","type":"Person"},{"id":"https://www.moma.org/data/person/7297","type":"Person"},{"id":"https://www.moma.org/data/person/7677","type":"Person"},{"id":"https://www.moma.org/data/person/7278","type":"Person"},{"id":"https://www.moma.org/data/person/8028","type":"Person"},{"id":"https://www.moma.org/data/person/5772","type":"Person"},{"id":"https://www.moma.org/data/person/5999","type":"Person"},{"id":"https://www.moma.org/data/person/8071","type":"Person"},{"id":"https://www.moma.org/data/person/7275","type":"Person"},{"id":"https://www.moma.org/data/person/18549","type":"Person"},{"id":"https://www.moma.org/data/person/7527","type":"Person"},{"id":"https://www.moma.org/data/person/7532","type":"Person"},{"id":"https://www.moma.org/data/person/7277","type":"Person"},{"id":"https://www.moma.org/data/person/5544","type":"Person"},{"id":"https://www.moma.org/data/person/5817","type":"Person"},{"id":"https://www.moma.org/data/person/7533","type":"Person"},{"id":"https://www.moma.org/data/person/7534","type":"Person"},{"id":"https://www.moma.org/data/person/6111","type":"Person"},{"id":"https://www.moma.org/data/person/6611","type":"Person"},{"id":"https://www.moma.org/data/person/6706","type":"Person"},{"id":"https://www.moma.org/data/person/7285","type":"Person"},{"id":"https://www.moma.org/data/person/7458","type":"Person"},{"id":"https://www.moma.org/data/person/35946","type":"Person"},{"id":"https://www.moma.org/data/person/26969","type":"Person"},{"id":"https://www.moma.org/data/person/2819","type":"Person"},{"id":"https://www.moma.org/data/person/193","type":"Person"},{"id":"https://www.moma.org/data/person/289","type":"Person"},{"id":"https://www.moma.org/data/person/741","type":"Person"},{"id":"https://www.moma.org/data/person/143","type":"Person"},{"id":"https://www.moma.org/data/person/223","type":"Person"},{"id":"https://www.moma.org/data/person/1892","type":"Person"},{"id":"https://www.moma.org/data/person/126","type":"Person"},{"id":"https://www.moma.org/data/person/429","type":"Person"},{"id":"https://www.moma.org/data/person/718","type":"Person"},{"id":"https://www.moma.org/data/person/2540","type":"Person"},{"id":"https://www.moma.org/data/person/715","type":"Person"},{"id":"https://www.moma.org/data/person/2213","type":"Person"},{"id":"https://www.moma.org/data/person/1614","type":"Person"},{"id":"https://www.moma.org/data/person/394","type":"Person"},{"id":"https://www.moma.org/data/person/836","type":"Person"},{"id":"https://www.moma.org/data/person/2263","type":"Person"},{"id":"https://www.moma.org/data/person/908","type":"Person"},{"id":"https://www.moma.org/data/person/960","type":"Person"},{"id":"https://www.moma.org/data/person/1859","type":"Person"},{"id":"https://www.moma.org/data/person/1161","type":"Person"}]}