{"@context":"https://linked.art/ns/v1/linked-art.json","id":"https://www.moma.org/data/activity/21837","type":"Activity","classified_as":[{"id":"http://vocab.getty.edu/aat/300054766","type":"Type","_label":"Exhibiting"}],"identified_by":[{"type":"Name","classified_as":[{"id":"http://vocab.getty.edu/aat/300404670","type":"Type","_label":"Primary Name"}],"content":"Elizabeth Price: Choir"}],"carried_out_by":[{"id":"https://www.moma.org/data/group/inst13","type":"Group"},{"id":"https://www.moma.org/data/person/64700","type":"Person"},{"id":"https://www.moma.org/data/person/65119","type":"Person"}],"subject_of":[{"type":"LinguisticObject"}],"influenced_by":[{"id":"https://www.moma.org/data/person/64515","type":"Person"}]}