{"@context":"https://linked.art/ns/v1/linked-art.json","id":"https://www.moma.org/data/activity/22027","type":"Activity","classified_as":[{"id":"http://vocab.getty.edu/aat/300054766","type":"Type","_label":"Exhibiting"}],"identified_by":[{"type":"Name","classified_as":[{"id":"http://vocab.getty.edu/aat/300404670","type":"Type","_label":"Primary Name"}],"content":"Not Just For Laughs: The Art of Subversion"}],"carried_out_by":[{"id":"https://www.moma.org/data/group/inst13","type":"Group"},{"id":"https://www.moma.org/data/person/33005","type":"Person"}],"subject_of":[{"type":"LinguisticObject"}],"influenced_by":[{"id":"https://www.moma.org/data/person/1199","type":"Person"},{"id":"https://www.moma.org/data/person/65754","type":"Person"},{"id":"https://www.moma.org/data/person/66905","type":"Person"},{"id":"https://www.moma.org/data/person/66253","type":"Person"},{"id":"https://www.moma.org/data/person/116","type":"Person"},{"id":"https://www.moma.org/data/person/1132","type":"Person"},{"id":"https://www.moma.org/data/person/5581","type":"Person"},{"id":"https://www.moma.org/data/person/21034","type":"Person"},{"id":"https://www.moma.org/data/person/64975","type":"Person"},{"id":"https://www.moma.org/data/person/64134","type":"Person"},{"id":"https://www.moma.org/data/person/59688","type":"Person"},{"id":"https://www.moma.org/data/person/57179","type":"Person"},{"id":"https://www.moma.org/data/person/373","type":"Person"},{"id":"https://www.moma.org/data/person/22954","type":"Person"},{"id":"https://www.moma.org/data/person/5999","type":"Person"},{"id":"https://www.moma.org/data/person/20215","type":"Person"},{"id":"https://www.moma.org/data/person/19546","type":"Person"},{"id":"https://www.moma.org/data/person/17680","type":"Person"},{"id":"https://www.moma.org/data/person/7123","type":"Person"},{"id":"https://www.moma.org/data/person/57111","type":"Person"}]}