{"@context":"https://linked.art/ns/v1/linked-art.json","id":"https://www.moma.org/data/activity/2305","type":"Activity","classified_as":[{"id":"http://vocab.getty.edu/aat/300054766","type":"Type","_label":"Exhibiting"}],"identified_by":[{"type":"Name","classified_as":[{"id":"http://vocab.getty.edu/aat/300404670","type":"Type","_label":"Primary Name"}],"content":"On-Site: New Architecture in Spain"}],"carried_out_by":[{"id":"https://www.moma.org/data/group/inst3","type":"Group"}],"subject_of":[{"type":"LinguisticObject"}],"influenced_by":[{"id":"https://www.moma.org/data/group/18360","type":"Group"},{"id":"https://www.moma.org/data/group/14568","type":"Group"},{"id":"https://www.moma.org/data/group/18368","type":"Group"},{"id":"https://www.moma.org/data/group/18346","type":"Group"},{"id":"https://www.moma.org/data/group/18347","type":"Group"},{"id":"https://www.moma.org/data/group/18365","type":"Group"},{"id":"https://www.moma.org/data/group/18348","type":"Group"},{"id":"https://www.moma.org/data/group/18350","type":"Group"},{"id":"https://www.moma.org/data/group/16604","type":"Group"},{"id":"https://www.moma.org/data/person/18386","type":"Person"},{"id":"https://www.moma.org/data/group/18370","type":"Group"},{"id":"https://www.moma.org/data/group/18371","type":"Group"},{"id":"https://www.moma.org/data/group/7655","type":"Group"},{"id":"https://www.moma.org/data/group/18362","type":"Group"},{"id":"https://www.moma.org/data/group/18357","type":"Group"},{"id":"https://www.moma.org/data/group/18358","type":"Group"},{"id":"https://www.moma.org/data/person/18349","type":"Person"},{"id":"https://www.moma.org/data/group/18384","type":"Group"},{"id":"https://www.moma.org/data/group/8343","type":"Group"},{"id":"https://www.moma.org/data/group/7197","type":"Group"},{"id":"https://www.moma.org/data/group/18407","type":"Group"},{"id":"https://www.moma.org/data/person/16096","type":"Person"},{"id":"https://www.moma.org/data/group/8290","type":"Group"},{"id":"https://www.moma.org/data/group/18410","type":"Group"},{"id":"https://www.moma.org/data/group/6646","type":"Group"},{"id":"https://www.moma.org/data/group/18413","type":"Group"},{"id":"https://www.moma.org/data/group/18417","type":"Group"},{"id":"https://www.moma.org/data/group/18342","type":"Group"},{"id":"https://www.moma.org/data/group/18382","type":"Group"},{"id":"https://www.moma.org/data/group/18416","type":"Group"},{"id":"https://www.moma.org/data/group/18380","type":"Group"},{"id":"https://www.moma.org/data/group/18378","type":"Group"},{"id":"https://www.moma.org/data/group/18374","type":"Group"},{"id":"https://www.moma.org/data/group/17297","type":"Group"},{"id":"https://www.moma.org/data/group/18345","type":"Group"},{"id":"https://www.moma.org/data/person/8306","type":"Person"}]}