{"@context":"https://linked.art/ns/v1/linked-art.json","id":"https://www.moma.org/data/activity/2729","type":"Activity","classified_as":[{"id":"http://vocab.getty.edu/aat/300054766","type":"Type","_label":"Exhibiting"}],"identified_by":[{"type":"Name","classified_as":[{"id":"http://vocab.getty.edu/aat/300404670","type":"Type","_label":"Primary Name"}],"content":"Figures: Sculpture in the Auditorium"}],"carried_out_by":[{"id":"https://www.moma.org/data/group/inst7","type":"Group"}],"subject_of":[{"type":"LinguisticObject"}],"influenced_by":[{"id":"https://www.moma.org/data/person/4991","type":"Person"},{"id":"https://www.moma.org/data/person/57241","type":"Person"},{"id":"https://www.moma.org/data/person/57020","type":"Person"},{"id":"https://www.moma.org/data/person/57612","type":"Person"},{"id":"https://www.moma.org/data/person/57611","type":"Person"},{"id":"https://www.moma.org/data/person/57610","type":"Person"},{"id":"https://www.moma.org/data/person/57609","type":"Person"},{"id":"https://www.moma.org/data/person/57608","type":"Person"},{"id":"https://www.moma.org/data/person/57607","type":"Person"},{"id":"https://www.moma.org/data/person/57606","type":"Person"},{"id":"https://www.moma.org/data/person/57604","type":"Person"},{"id":"https://www.moma.org/data/person/57605","type":"Person"}]}