{"@context":"https://linked.art/ns/v1/linked-art.json","id":"https://www.moma.org/data/activity/28415","type":"Activity","classified_as":[{"id":"http://vocab.getty.edu/aat/300054766","type":"Type","_label":"Exhibiting"}],"identified_by":[{"type":"Name","classified_as":[{"id":"http://vocab.getty.edu/aat/300404670","type":"Type","_label":"Primary Name"}],"content":"Whitney Biennial 2012"}],"carried_out_by":[{"id":"https://www.moma.org/data/group/inst10","type":"Group"}],"subject_of":[{"type":"LinguisticObject"}],"influenced_by":[{"id":"https://www.moma.org/data/person/70559","type":"Person"},{"id":"https://www.moma.org/data/person/70554","type":"Person"},{"id":"https://www.moma.org/data/person/19451","type":"Person"},{"id":"https://www.moma.org/data/person/70534","type":"Person"},{"id":"https://www.moma.org/data/person/2919","type":"Person"},{"id":"https://www.moma.org/data/person/70565","type":"Person"},{"id":"https://www.moma.org/data/person/70543","type":"Person"},{"id":"https://www.moma.org/data/person/70532","type":"Person"},{"id":"https://www.moma.org/data/person/70560","type":"Person"},{"id":"https://www.moma.org/data/person/13440","type":"Person"},{"id":"https://www.moma.org/data/person/70529","type":"Person"},{"id":"https://www.moma.org/data/person/70530","type":"Person"},{"id":"https://www.moma.org/data/person/70567","type":"Person"},{"id":"https://www.moma.org/data/person/70570","type":"Person"},{"id":"https://www.moma.org/data/person/70540","type":"Person"},{"id":"https://www.moma.org/data/person/70555","type":"Person"},{"id":"https://www.moma.org/data/person/70551","type":"Person"},{"id":"https://www.moma.org/data/person/70541","type":"Person"},{"id":"https://www.moma.org/data/group/70562","type":"Group"},{"id":"https://www.moma.org/data/person/70568","type":"Person"},{"id":"https://www.moma.org/data/person/70569","type":"Person"},{"id":"https://www.moma.org/data/person/70230","type":"Person"},{"id":"https://www.moma.org/data/person/70573","type":"Person"},{"id":"https://www.moma.org/data/person/70561","type":"Person"},{"id":"https://www.moma.org/data/person/70553","type":"Person"},{"id":"https://www.moma.org/data/person/70556","type":"Person"},{"id":"https://www.moma.org/data/person/70572","type":"Person"},{"id":"https://www.moma.org/data/person/19058","type":"Person"},{"id":"https://www.moma.org/data/group/71157","type":"Group"},{"id":"https://www.moma.org/data/person/18826","type":"Person"},{"id":"https://www.moma.org/data/person/71152","type":"Person"},{"id":"https://www.moma.org/data/person/70544","type":"Person"},{"id":"https://www.moma.org/data/person/70535","type":"Person"},{"id":"https://www.moma.org/data/person/509","type":"Person"},{"id":"https://www.moma.org/data/person/70548","type":"Person"},{"id":"https://www.moma.org/data/person/70566","type":"Person"},{"id":"https://www.moma.org/data/group/71155","type":"Group"},{"id":"https://www.moma.org/data/person/71154","type":"Person"},{"id":"https://www.moma.org/data/person/70550","type":"Person"},{"id":"https://www.moma.org/data/person/70564","type":"Person"},{"id":"https://www.moma.org/data/person/70558","type":"Person"},{"id":"https://www.moma.org/data/person/70552","type":"Person"},{"id":"https://www.moma.org/data/person/71153","type":"Person"},{"id":"https://www.moma.org/data/person/70563","type":"Person"},{"id":"https://www.moma.org/data/person/34103","type":"Person"},{"id":"https://www.moma.org/data/person/70528","type":"Person"},{"id":"https://www.moma.org/data/person/70539","type":"Person"},{"id":"https://www.moma.org/data/person/70346","type":"Person"},{"id":"https://www.moma.org/data/person/70546","type":"Person"},{"id":"https://www.moma.org/data/person/70545","type":"Person"},{"id":"https://www.moma.org/data/person/70479","type":"Person"}]}