{"@context":"https://linked.art/ns/v1/linked-art.json","id":"https://www.moma.org/data/activity/2858","type":"Activity","classified_as":[{"id":"http://vocab.getty.edu/aat/300054766","type":"Type","_label":"Exhibiting"}],"identified_by":[{"type":"Name","classified_as":[{"id":"http://vocab.getty.edu/aat/300404670","type":"Type","_label":"Primary Name"}],"content":"Orpheus Selection: In Search of Darkness"}],"carried_out_by":[{"id":"https://www.moma.org/data/group/inst7","type":"Group"}],"subject_of":[{"type":"LinguisticObject"}],"influenced_by":[{"id":"https://www.moma.org/data/person/7549","type":"Person"},{"id":"https://www.moma.org/data/person/21220","type":"Person"},{"id":"https://www.moma.org/data/person/6062","type":"Person"},{"id":"https://www.moma.org/data/person/5630","type":"Person"},{"id":"https://www.moma.org/data/person/3174","type":"Person"},{"id":"https://www.moma.org/data/person/7097","type":"Person"},{"id":"https://www.moma.org/data/person/16977","type":"Person"},{"id":"https://www.moma.org/data/person/60120","type":"Person"},{"id":"https://www.moma.org/data/person/60113","type":"Person"},{"id":"https://www.moma.org/data/person/60114","type":"Person"},{"id":"https://www.moma.org/data/person/60108","type":"Person"},{"id":"https://www.moma.org/data/person/60099","type":"Person"},{"id":"https://www.moma.org/data/person/60111","type":"Person"},{"id":"https://www.moma.org/data/person/60115","type":"Person"},{"id":"https://www.moma.org/data/person/60116","type":"Person"},{"id":"https://www.moma.org/data/person/60109","type":"Person"},{"id":"https://www.moma.org/data/person/60110","type":"Person"},{"id":"https://www.moma.org/data/person/60112","type":"Person"},{"id":"https://www.moma.org/data/person/60119","type":"Person"},{"id":"https://www.moma.org/data/person/60117","type":"Person"},{"id":"https://www.moma.org/data/person/60121","type":"Person"},{"id":"https://www.moma.org/data/person/60118","type":"Person"}]}