{"@context":"https://linked.art/ns/v1/linked-art.json","id":"https://www.moma.org/data/activity/3147","type":"Activity","classified_as":[{"id":"http://vocab.getty.edu/aat/300054766","type":"Type","_label":"Exhibiting"}],"identified_by":[{"type":"Name","classified_as":[{"id":"http://vocab.getty.edu/aat/300404670","type":"Type","_label":"Primary Name"}],"content":"Video (Winter 1979–1980)"}],"carried_out_by":[{"id":"https://www.moma.org/data/group/inst7","type":"Group"}],"subject_of":[{"type":"LinguisticObject"}],"influenced_by":[{"id":"https://www.moma.org/data/person/24765","type":"Person"},{"id":"https://www.moma.org/data/person/8159","type":"Person"},{"id":"https://www.moma.org/data/person/32847","type":"Person"},{"id":"https://www.moma.org/data/person/56855","type":"Person"},{"id":"https://www.moma.org/data/person/58710","type":"Person"},{"id":"https://www.moma.org/data/person/56856","type":"Person"}]}