{"@context":"https://linked.art/ns/v1/linked-art.json","id":"https://www.moma.org/data/activity/4042","type":"Activity","classified_as":[{"id":"http://vocab.getty.edu/aat/300054766","type":"Type","_label":"Exhibiting"}],"identified_by":[{"type":"Name","classified_as":[{"id":"http://vocab.getty.edu/aat/300404670","type":"Type","_label":"Primary Name"}],"content":"Queer Voice"}],"carried_out_by":[{"id":"https://www.moma.org/data/group/inst15","type":"Group"}],"subject_of":[{"type":"LinguisticObject"}],"influenced_by":[{"id":"https://www.moma.org/data/person/23252","type":"Person"},{"id":"https://www.moma.org/data/person/5270","type":"Person"},{"id":"https://www.moma.org/data/person/20947","type":"Person"},{"id":"https://www.moma.org/data/person/6510","type":"Person"},{"id":"https://www.moma.org/data/person/25934","type":"Person"},{"id":"https://www.moma.org/data/person/5966","type":"Person"},{"id":"https://www.moma.org/data/person/23352","type":"Person"}]}