{"@context":"https://linked.art/ns/v1/linked-art.json","id":"https://www.moma.org/data/activity/576","type":"Activity","classified_as":[{"id":"http://vocab.getty.edu/aat/300054766","type":"Type","_label":"Exhibiting"}],"identified_by":[{"type":"Name","classified_as":[{"id":"http://vocab.getty.edu/aat/300404670","type":"Type","_label":"Primary Name"}],"content":"15 Americans"}],"carried_out_by":[{"id":"https://www.moma.org/data/group/inst3","type":"Group"},{"id":"https://www.moma.org/data/person/27083","type":"Person"}],"subject_of":[{"type":"LinguisticObject"}],"influenced_by":[{"id":"https://www.moma.org/data/person/2893","type":"Person"},{"id":"https://www.moma.org/data/person/2963","type":"Person"},{"id":"https://www.moma.org/data/person/4848","type":"Person"},{"id":"https://www.moma.org/data/person/4487","type":"Person"},{"id":"https://www.moma.org/data/person/4820","type":"Person"},{"id":"https://www.moma.org/data/person/3116","type":"Person"},{"id":"https://www.moma.org/data/person/3416","type":"Person"},{"id":"https://www.moma.org/data/person/6082","type":"Person"},{"id":"https://www.moma.org/data/person/5444","type":"Person"},{"id":"https://www.moma.org/data/person/5667","type":"Person"},{"id":"https://www.moma.org/data/person/1770","type":"Person"},{"id":"https://www.moma.org/data/person/383","type":"Person"},{"id":"https://www.moma.org/data/person/1183","type":"Person"},{"id":"https://www.moma.org/data/person/2098","type":"Person"},{"id":"https://www.moma.org/data/person/1465","type":"Person"}]}