{"@context":"https://linked.art/ns/v1/linked-art.json","id":"https://www.moma.org/data/activity/78","type":"Activity","classified_as":[{"id":"http://vocab.getty.edu/aat/300054766","type":"Type","_label":"Exhibiting"}],"identified_by":[{"type":"Name","classified_as":[{"id":"http://vocab.getty.edu/aat/300404670","type":"Type","_label":"Primary Name"}],"content":"Modern Exposition Architecture"}],"carried_out_by":[{"id":"https://www.moma.org/data/group/inst3","type":"Group"},{"id":"https://www.moma.org/data/person/26963","type":"Person"}],"subject_of":[{"type":"LinguisticObject"}],"influenced_by":[{"id":"https://www.moma.org/data/person/3281","type":"Person"},{"id":"https://www.moma.org/data/person/5242","type":"Person"},{"id":"https://www.moma.org/data/person/16115","type":"Person"},{"id":"https://www.moma.org/data/person/6846","type":"Person"},{"id":"https://www.moma.org/data/person/6990","type":"Person"},{"id":"https://www.moma.org/data/person/7063","type":"Person"},{"id":"https://www.moma.org/data/person/10182","type":"Person"},{"id":"https://www.moma.org/data/person/7659","type":"Person"},{"id":"https://www.moma.org/data/person/28946","type":"Person"},{"id":"https://www.moma.org/data/person/30235","type":"Person"},{"id":"https://www.moma.org/data/person/28950","type":"Person"},{"id":"https://www.moma.org/data/person/28949","type":"Person"},{"id":"https://www.moma.org/data/person/28947","type":"Person"},{"id":"https://www.moma.org/data/person/30234","type":"Person"},{"id":"https://www.moma.org/data/person/28945","type":"Person"},{"id":"https://www.moma.org/data/person/28944","type":"Person"},{"id":"https://www.moma.org/data/person/27550","type":"Person"},{"id":"https://www.moma.org/data/person/28941","type":"Person"},{"id":"https://www.moma.org/data/person/30233","type":"Person"},{"id":"https://www.moma.org/data/person/30232","type":"Person"},{"id":"https://www.moma.org/data/person/28942","type":"Person"},{"id":"https://www.moma.org/data/person/28943","type":"Person"},{"id":"https://www.moma.org/data/person/28948","type":"Person"},{"id":"https://www.moma.org/data/person/26","type":"Person"},{"id":"https://www.moma.org/data/person/2264","type":"Person"},{"id":"https://www.moma.org/data/person/2343","type":"Person"}]}