{"@context":"https://linked.art/ns/v1/linked-art.json","id":"https://www.moma.org/data/activity/933","type":"Activity","classified_as":[{"id":"http://vocab.getty.edu/aat/300054766","type":"Type","_label":"Exhibiting"}],"identified_by":[{"type":"Name","classified_as":[{"id":"http://vocab.getty.edu/aat/300404670","type":"Type","_label":"Primary Name"}],"content":"Recent Acquisitions: Design Collection"}],"carried_out_by":[{"id":"https://www.moma.org/data/group/inst3","type":"Group"},{"id":"https://www.moma.org/data/person/8274","type":"Person"}],"subject_of":[{"type":"LinguisticObject"}],"influenced_by":[{"id":"https://www.moma.org/data/person/4995","type":"Person"},{"id":"https://www.moma.org/data/person/3972","type":"Person"},{"id":"https://www.moma.org/data/person/3613","type":"Person"},{"id":"https://www.moma.org/data/person/3422","type":"Person"},{"id":"https://www.moma.org/data/person/4073","type":"Person"},{"id":"https://www.moma.org/data/person/4003","type":"Person"},{"id":"https://www.moma.org/data/person/4089","type":"Person"},{"id":"https://www.moma.org/data/person/5288","type":"Person"},{"id":"https://www.moma.org/data/person/4587","type":"Person"},{"id":"https://www.moma.org/data/person/4863","type":"Person"},{"id":"https://www.moma.org/data/person/3276","type":"Person"},{"id":"https://www.moma.org/data/person/4304","type":"Person"},{"id":"https://www.moma.org/data/person/2995","type":"Person"},{"id":"https://www.moma.org/data/person/3745","type":"Person"},{"id":"https://www.moma.org/data/person/5071","type":"Person"},{"id":"https://www.moma.org/data/person/3678","type":"Person"},{"id":"https://www.moma.org/data/person/4790","type":"Person"},{"id":"https://www.moma.org/data/person/4072","type":"Person"},{"id":"https://www.moma.org/data/person/4962","type":"Person"},{"id":"https://www.moma.org/data/person/3152","type":"Person"},{"id":"https://www.moma.org/data/person/3004","type":"Person"},{"id":"https://www.moma.org/data/person/4993","type":"Person"},{"id":"https://www.moma.org/data/person/5156","type":"Person"},{"id":"https://www.moma.org/data/group/9520","type":"Group"},{"id":"https://www.moma.org/data/group/13284","type":"Group"},{"id":"https://www.moma.org/data/person/5647","type":"Person"},{"id":"https://www.moma.org/data/group/9518","type":"Group"},{"id":"https://www.moma.org/data/person/5705","type":"Person"},{"id":"https://www.moma.org/data/group/9183","type":"Group"},{"id":"https://www.moma.org/data/group/8556","type":"Group"},{"id":"https://www.moma.org/data/group/9059","type":"Group"},{"id":"https://www.moma.org/data/group/9190","type":"Group"},{"id":"https://www.moma.org/data/group/23529","type":"Group"},{"id":"https://www.moma.org/data/group/8974","type":"Group"},{"id":"https://www.moma.org/data/group/9525","type":"Group"},{"id":"https://www.moma.org/data/group/9528","type":"Group"},{"id":"https://www.moma.org/data/group/9207","type":"Group"},{"id":"https://www.moma.org/data/group/9246","type":"Group"},{"id":"https://www.moma.org/data/group/9522","type":"Group"},{"id":"https://www.moma.org/data/group/9270","type":"Group"},{"id":"https://www.moma.org/data/group/9271","type":"Group"},{"id":"https://www.moma.org/data/group/9438","type":"Group"},{"id":"https://www.moma.org/data/group/9521","type":"Group"},{"id":"https://www.moma.org/data/group/9529","type":"Group"},{"id":"https://www.moma.org/data/group/9161","type":"Group"},{"id":"https://www.moma.org/data/group/9523","type":"Group"},{"id":"https://www.moma.org/data/person/5510","type":"Person"},{"id":"https://www.moma.org/data/group/8482","type":"Group"},{"id":"https://www.moma.org/data/group/13179","type":"Group"},{"id":"https://www.moma.org/data/group/9527","type":"Group"},{"id":"https://www.moma.org/data/person/5954","type":"Person"},{"id":"https://www.moma.org/data/person/26991","type":"Person"},{"id":"https://www.moma.org/data/group/8503","type":"Group"},{"id":"https://www.moma.org/data/group/8363","type":"Group"},{"id":"https://www.moma.org/data/group/9038","type":"Group"},{"id":"https://www.moma.org/data/group/17092","type":"Group"},{"id":"https://www.moma.org/data/group/9044","type":"Group"},{"id":"https://www.moma.org/data/person/5805","type":"Person"},{"id":"https://www.moma.org/data/person/5593","type":"Person"},{"id":"https://www.moma.org/data/person/6817","type":"Person"},{"id":"https://www.moma.org/data/group/9526","type":"Group"},{"id":"https://www.moma.org/data/person/5882","type":"Person"},{"id":"https://www.moma.org/data/person/6811","type":"Person"},{"id":"https://www.moma.org/data/group/8362","type":"Group"},{"id":"https://www.moma.org/data/person/6815","type":"Person"},{"id":"https://www.moma.org/data/person/6829","type":"Person"},{"id":"https://www.moma.org/data/group/9530","type":"Group"},{"id":"https://www.moma.org/data/group/14359","type":"Group"},{"id":"https://www.moma.org/data/group/9090","type":"Group"},{"id":"https://www.moma.org/data/person/6833","type":"Person"},{"id":"https://www.moma.org/data/person/6318","type":"Person"},{"id":"https://www.moma.org/data/group/8360","type":"Group"},{"id":"https://www.moma.org/data/group/14121","type":"Group"},{"id":"https://www.moma.org/data/group/8350","type":"Group"},{"id":"https://www.moma.org/data/group/31895","type":"Group"},{"id":"https://www.moma.org/data/group/31892","type":"Group"},{"id":"https://www.moma.org/data/group/31891","type":"Group"},{"id":"https://www.moma.org/data/person/31890","type":"Person"},{"id":"https://www.moma.org/data/group/31893","type":"Group"},{"id":"https://www.moma.org/data/group/31724","type":"Group"},{"id":"https://www.moma.org/data/person/31894","type":"Person"},{"id":"https://www.moma.org/data/person/2524","type":"Person"},{"id":"https://www.moma.org/data/person/2310","type":"Person"},{"id":"https://www.moma.org/data/person/727","type":"Person"},{"id":"https://www.moma.org/data/person/905","type":"Person"},{"id":"https://www.moma.org/data/group/2286","type":"Group"},{"id":"https://www.moma.org/data/person/49","type":"Person"},{"id":"https://www.moma.org/data/person/2421","type":"Person"},{"id":"https://www.moma.org/data/person/146","type":"Person"},{"id":"https://www.moma.org/data/person/2193","type":"Person"},{"id":"https://www.moma.org/data/person/759","type":"Person"},{"id":"https://www.moma.org/data/person/987","type":"Person"},{"id":"https://www.moma.org/data/person/988","type":"Person"},{"id":"https://www.moma.org/data/person/1544","type":"Person"},{"id":"https://www.moma.org/data/person/1848","type":"Person"},{"id":"https://www.moma.org/data/person/1711","type":"Person"},{"id":"https://www.moma.org/data/person/1363","type":"Person"},{"id":"https://www.moma.org/data/person/1144","type":"Person"},{"id":"https://www.moma.org/data/person/784","type":"Person"},{"id":"https://www.moma.org/data/person/2662","type":"Person"}]}