{"@context":"https://linked.art/ns/v1/linked-art.json","id":"https://www.moma.org/data/person/23589","type":"Person","identified_by":[{"type":"Name","content":"Elena Izcue"},{"type":"Identifier","content":"39243","attributed_by":[{"type":"AttributeAssignment","carried_out_by":[{"id":"https://www.moma.org/data/group/inst2","type":"Group"}]}]}],"referred_to_by":[{"type":"LinguisticObject","classified_as":[{"id":"http://vocab.getty.edu/aat/300435422","type":"Type","_label":"Biography Statement","classified_as":[{"id":"http://vocab.getty.edu/aat/300418049","type":"Type","_label":"Brief Text"}]}],"content":"Peruvian, 1889–1970"}],"born":{"type":"Birth","timespan":{"type":"TimeSpan","identified_by":[{"type":"Name","classified_as":[{"id":"http://vocab.getty.edu/aat/300404669","type":"Type","_label":"Display Title"}],"content":"1889"}],"begin_of_the_begin":"1889-01-01T00:00:00Z","end_of_the_end":"1889-12-31T23:59:59Z"}},"died":{"type":"Death","timespan":{"type":"TimeSpan","identified_by":[{"type":"Name","classified_as":[{"id":"http://vocab.getty.edu/aat/300404669","type":"Type","_label":"Display Title"}],"content":"1970"}],"begin_of_the_begin":"1970-01-01T00:00:00Z","end_of_the_end":"1970-12-31T23:59:59Z"}},"equivalent":[{"id":"http://vocab.getty.edu/ulan/500117272","type":"Person"},{"id":"http://viaf.org/viaf/73980468","type":"Person"}]}