{"@context":"https://linked.art/ns/v1/linked-art.json","id":"https://www.moma.org/data/person/56753","type":"Person","identified_by":[{"type":"Name","content":"Peggy Cyphers"},{"type":"Identifier","content":"70816","attributed_by":[{"type":"AttributeAssignment","carried_out_by":[{"id":"https://www.moma.org/data/group/inst2","type":"Group"}]}]}],"born":{"type":"Birth","timespan":{"type":"TimeSpan","identified_by":[{"type":"Name","classified_as":[{"id":"http://vocab.getty.edu/aat/300404669","type":"Type","_label":"Display Title"}],"content":"1954"}],"begin_of_the_begin":"1954-01-01T00:00:00Z","end_of_the_end":"1954-12-31T23:59:59Z"}},"equivalent":[{"id":"http://vocab.getty.edu/ulan/500106531","type":"Person"},{"id":"http://www.wikidata.org/entity/Q19802587","type":"Person"},{"id":"http://viaf.org/viaf/96476122","type":"Person"}]}